unihan_db/__about__.py
unihan_db/__init__.py
unihan_db/bootstrap.py
unihan_db/importer.py
unihan_db/tables.py
unihan_db-0.18.0.dist-info/METADATA
unihan_db-0.18.0.dist-info/WHEEL
unihan_db-0.18.0.dist-info/licenses/LICENSE
unihan_db-0.18.0.dist-info/RECORD
