Metadata-Version: 2.4
Name: unihan_db
Version: 0.18.0
Summary: SQLAlchemy models for UNIHAN CJK database
Project-URL: Bug Tracker, https://github.com/cihai/unihan-db/issues
Project-URL: Documentation, https://unihan-db.git-pull.com
Project-URL: Repository, https://github.com/cihai/unihan-db
Project-URL: Release notes, https://github.com/cihai/unihan-db/blob/master/CHANGES
Author-email: Tony Narlock <tony@git-pull.com>
License: MIT
License-File: LICENSE
Keywords: chinese,cjk,database,japanese,sql,sqlalchemy,unihan
Classifier: Development Status :: 2 - Pre-Alpha
Classifier: Environment :: Web Environment
Classifier: Intended Audience :: Developers
Classifier: License :: OSI Approved :: MIT License
Classifier: Programming Language :: Python
Classifier: Programming Language :: Python :: 3
Classifier: Programming Language :: Python :: 3.9
Classifier: Programming Language :: Python :: 3.10
Classifier: Programming Language :: Python :: 3.11
Classifier: Programming Language :: Python :: 3.13
Classifier: Programming Language :: Python :: Implementation :: PyPy
Classifier: Topic :: Database
Classifier: Topic :: Software Development :: Internationalization
Classifier: Topic :: Software Development :: Localization
Classifier: Topic :: Utilities
Requires-Python: <4.0,>=3.9
Requires-Dist: appdirs
Requires-Dist: sqlalchemy>=2
Requires-Dist: unihan-etl~=0.37.0
